moffman/__init__.py
moffman/calendar_handler.py
moffman/cli.py
moffman/default_config.yaml
moffman/dynamic_configs.py
moffman/http_handler.py
moffman/moffman.py
moffman/persistent_store.py
moffman/spreadsheet_handler.py
moffman/utils.py
moffman-0.4.0.dist-info/entry_points.txt
moffman-0.4.0.dist-info/LICENSE
moffman-0.4.0.dist-info/WHEEL
moffman-0.4.0.dist-info/METADATA
moffman-0.4.0.dist-info/RECORD
