Metadata-Version: 2.1
Name: moffman
Version: 0.4.0
Summary: Microservice for managing team attendance in multiple offices.
Home-page: https://github.com/JNevrly/moffman
License: MIT
Author: Josef Nevrly
Author-email: josef.nevrly@gmail.com
Requires-Python: >=3.8.0,<4.0.0
Classifier: Development Status :: 2 - Pre-Alpha
Classifier: Intended Audience :: Developers
Classifier: License :: OSI Approved :: MIT License
Classifier: Natural Language :: English
Classifier: Programming Language :: Python :: 3
Classifier: Programming Language :: Python :: 3.10
Classifier: Programming Language :: Python :: 3.8
Classifier: Programming Language :: Python :: 3.9
Requires-Dist: APScheduler (>=3.9.1,<4.0.0)
Requires-Dist: aiogoogle (>=4.2.0,<5.0.0)
Requires-Dist: aiohttp (>=3.7.4,<4.0.0)
Requires-Dist: arrow (>=1.2.2,<2.0.0)
Requires-Dist: click (>=8.0.1,<9.0.0)
Requires-Dist: onacol (>=0.3.0,<0.4.0)
Requires-Dist: sockjs (>=0.11.0,<0.12.0)
Project-URL: Documentation, https://github.com/JNevrly/moffman
Project-URL: Repository, https://github.com/JNevrly/moffman
